odoo/addons/stock_service_level/README.rst
odoo/addons/stock_service_level/__init__.py
odoo/addons/stock_service_level/__manifest__.py
odoo/addons/stock_service_level/i18n/fr.po
odoo/addons/stock_service_level/i18n/stock_service_level.pot
odoo/addons/stock_service_level/models/__init__.py
odoo/addons/stock_service_level/models/stock_move.py
odoo/addons/stock_service_level/models/stock_rule.py
odoo/addons/stock_service_level/models/stock_service_level.py
odoo/addons/stock_service_level/readme/CONTRIBUTORS.rst
odoo/addons/stock_service_level/readme/DESCRIPTION.rst
odoo/addons/stock_service_level/security/ir.model.access.csv
odoo/addons/stock_service_level/static/description/icon.png
odoo/addons/stock_service_level/static/description/index.html
odoo/addons/stock_service_level/tests/__init__.py
odoo/addons/stock_service_level/tests/common.py
odoo/addons/stock_service_level/tests/test_stock_service_level.py
odoo/addons/stock_service_level/views/stock_picking_views.xml
odoo/addons/stock_service_level/views/stock_service_level.xml
odoo14_addon_stock_service_level-14.0.1.0.1.dist-info/METADATA
odoo14_addon_stock_service_level-14.0.1.0.1.dist-info/WHEEL
odoo14_addon_stock_service_level-14.0.1.0.1.dist-info/top_level.txt
odoo14_addon_stock_service_level-14.0.1.0.1.dist-info/RECORD
